{
  "date": "2026-04-10",
  "sources": {
    "AI타임스 - 전체기사": {
      "total": 34,
      "cross": 0,
      "rate": 0.0
    },
    "Feed: Artificial Intelligence Latest": {
      "total": 4,
      "cross": 0,
      "rate": 0.0
    },
    "ITmedia AI＋ 最新記事一覧": {
      "total": 13,
      "cross": 2,
      "rate": 0.154
    },
    "MarkTechPost": {
      "total": 4,
      "cross": 1,
      "rate": 0.25
    },
    "AI | The Verge": {
      "total": 5,
      "cross": 2,
      "rate": 0.4
    },
    "AI News & Artificial Intelligence | TechCrunch": {
      "total": 9,
      "cross": 4,
      "rate": 0.444
    },
    "Biz & IT - Ars Technica": {
      "total": 1,
      "cross": 0,
      "rate": 0.0
    },
    "The Decoder": {
      "total": 8,
      "cross": 2,
      "rate": 0.25
    },
    "AI News": {
      "total": 2,
      "cross": 1,
      "rate": 0.5
    },
    "The Rundown AI": {
      "total": 1,
      "cross": 1,
      "rate": 1.0
    }
  }
}